llama_index/readers/asana/__init__.py
llama_index/readers/asana/base.py
llama_index_readers_asana-0.4.1.dist-info/METADATA
llama_index_readers_asana-0.4.1.dist-info/WHEEL
llama_index_readers_asana-0.4.1.dist-info/licenses/LICENSE
llama_index_readers_asana-0.4.1.dist-info/RECORD
