Metadata-Version: 2.4
Name: llama-index-readers-asana
Version: 0.4.1
Summary: llama-index readers asana integration
Author-email: Your Name <you@example.com>
Maintainer: daveey
License-Expression: MIT
License-File: LICENSE
Requires-Python: <4.0,>=3.9
Requires-Dist: asana<6,>=5.0.3
Requires-Dist: llama-index-core<0.15,>=0.13.0
